<?xml version = '1.0' encoding = 'UTF-8'?>
<Relation class="oracle.dbtools.crest.model.design.logical.Relation" name="Relation_5" directorySegmentName="seg_0" id="58BA81CE-D0A3-C1F9-9943-DFD5B30EE76F">
<createdBy>Intimedia7</createdBy>
<createdTime>2015-06-20 00:37:13 UTC</createdTime>
<generatorID>Generado por el Usuario</generatorID>
<ownerDesignName>diseno-gama</ownerDesignName>
<sourcePk>7390568C-ECD3-1591-C63B-8705AB17F706</sourcePk>
<identifying>false</identifying>
<optionalSource>true</optionalSource>
<optionalTarget>true</optionalTarget>
<sourceCardinality>1</sourceCardinality>
<sourceEntity>16DA5CB6-85F6-574A-C173-C06D0069C325</sourceEntity>
<targetCardinalityString>*</targetCardinalityString>
<targetEntity>8ECDA317-B522-D064-4564-6F4C6C66C105</targetEntity>
<transferable>true</transferable>
<deleteRule>NO ACTION</deleteRule>
</Relation>